ops_automate/__init__.py
ops_automate/influx_alert/__init__.py
ops_automate/influx_alert/client.py
ops_automate/influx_alert/endpoint.py
ops_automate/influx_alert/endpoints/__init__.py
ops_automate/influx_alert/endpoints/automate.py
ops_automate/influx_alert/endpoints/common.py
ops_automate/influx_alert/endpoints/extensions.py
ops_automate/influx_alert/endpoints/network.py
ops_automate/influx_alert/endpoints/vmware.py
ops_automate/telegraf_config/__init__.py
ops_automate/telegraf_config/build_config.py
ops_automate/telegraf_config/build_telegraf_config.py
OpsAutomate-0.0.8.dist-info/LICENSE
OpsAutomate-0.0.8.dist-info/METADATA
OpsAutomate-0.0.8.dist-info/WHEEL
OpsAutomate-0.0.8.dist-info/top_level.txt
OpsAutomate-0.0.8.dist-info/RECORD
