Metadata-Version: 2.1
Name: OpsAutomate
Version: 0.0.8
Summary: ops automate
Home-page: https://github.com/houm01/OpsAutomate
License-File: LICENSE
